stratumus/__init__.py
stratumus/stratumus.py
stratumus-0.0.16.dist-info/LICENSE.txt
stratumus-0.0.16.dist-info/METADATA
stratumus-0.0.16.dist-info/WHEEL
stratumus-0.0.16.dist-info/entry_points.txt
stratumus-0.0.16.dist-info/top_level.txt
stratumus-0.0.16.dist-info/RECORD
