Metadata-Version: 2.1
Name: stratumus
Version: 0.0.16
Summary: Layered Yaml Python Configuration
Home-page: https://github.com/jamesboehmer/stratumus
Author: James Boehmer
Author-email: james.boehmer@gmail.com
License: GPL
Keywords: layered configuration yaml
Platform: any
Classifier: Development Status :: 1 - Planning
Classifier: Intended Audience :: Developers
Classifier: License :: OSI Approved :: GNU General Public License v3 or later (GPLv3+)
Classifier: Programming Language :: Python :: 2.7
Classifier: Programming Language :: Python :: 3.6
Requires-Dist: HiYaPyCo (==0.4.8)
